<?xml version="1.0" encoding="UTF-8"?>
<language xmlns="http://www.woltlab.com" xmlns:xsi="http://www.w3.org/2001/XMLSchema-instance" xsi:schemaLocation="http://www.woltlab.com/XSD/language.xsd" languagecode="en">
	<category name="wcf.acp.package">
		<item name="wcf.acp.package.step.install.PageMenuPackageInstallationPlugin"><![CDATA[Installing menu items ...]]></item>
		<item name="wcf.acp.package.step.uninstall.PageMenuPackageInstallationPlugin"><![CDATA[Unistalling menu items ...]]></item>
		<item name="wcf.acp.package.step.update.PageMenuPackageInstallationPlugin"><![CDATA[Updating menu items ...]]></item>
	</category>
</language>